rwmutex/__init__.py
rwmutex/mux.py
rwmutex-1.1.dist-info/LICENSE
rwmutex-1.1.dist-info/METADATA
rwmutex-1.1.dist-info/WHEEL
rwmutex-1.1.dist-info/top_level.txt
rwmutex-1.1.dist-info/RECORD
